LICENSE
MANIFEST.in
README.md
setup.py
Bio_Eutils/__init__.py
Bio_Eutils.egg-info/PKG-INFO
Bio_Eutils.egg-info/SOURCES.txt
Bio_Eutils.egg-info/dependency_links.txt
Bio_Eutils.egg-info/top_level.txt
Bio_Eutils/Entrez/Parser.py
Bio_Eutils/Entrez/__init__.py
Bio_Eutils/Entrez/DTDs/Docsum_3_0.dtd
Bio_Eutils/Entrez/DTDs/Docsum_3_0.mod.dtd
Bio_Eutils/Entrez/DTDs/Docsum_3_1.dtd
Bio_Eutils/Entrez/DTDs/Docsum_3_1.mod.dtd
Bio_Eutils/Entrez/DTDs/Docsum_3_2.dtd
Bio_Eutils/Entrez/DTDs/Docsum_3_2.mod.dtd
Bio_Eutils/Entrez/DTDs/Docsum_3_3.dtd
Bio_Eutils/Entrez/DTDs/Docsum_3_3.mod.dtd
Bio_Eutils/Entrez/DTDs/Docsum_3_4.dtd
Bio_Eutils/Entrez/DTDs/Docsum_3_4.mod.dtd
Bio_Eutils/Entrez/DTDs/EMBL_General.dtd
Bio_Eutils/Entrez/DTDs/EMBL_General.mod.dtd
Bio_Eutils/Entrez/DTDs/GenBank_General.dtd
Bio_Eutils/Entrez/DTDs/GenBank_General.mod.dtd
Bio_Eutils/Entrez/DTDs/HomoloGene.dtd
Bio_Eutils/Entrez/DTDs/HomoloGene.mod.dtd
Bio_Eutils/Entrez/DTDs/INSD_INSDSeq.dtd
Bio_Eutils/Entrez/DTDs/INSD_INSDSeq.mod.dtd
Bio_Eutils/Entrez/DTDs/MMDB.dtd
Bio_Eutils/Entrez/DTDs/MMDB.mod.dtd
Bio_Eutils/Entrez/DTDs/MMDB_Chemical_graph.dtd
Bio_Eutils/Entrez/DTDs/MMDB_Chemical_graph.mod.dtd
Bio_Eutils/Entrez/DTDs/MMDB_Features.dtd
Bio_Eutils/Entrez/DTDs/MMDB_Features.mod.dtd
Bio_Eutils/Entrez/DTDs/MMDB_Structural_model.dtd
Bio_Eutils/Entrez/DTDs/MMDB_Structural_model.mod.dtd
Bio_Eutils/Entrez/DTDs/NCBI_Access.dtd
Bio_Eutils/Entrez/DTDs/NCBI_Access.mod.dtd
Bio_Eutils/Entrez/DTDs/NCBI_Biblio.dtd
Bio_Eutils/Entrez/DTDs/NCBI_Biblio.mod.dtd
Bio_Eutils/Entrez/DTDs/NCBI_BioSource.dtd
Bio_Eutils/Entrez/DTDs/NCBI_BioSource.mod.dtd
Bio_Eutils/Entrez/DTDs/NCBI_BioTree.dtd
Bio_Eutils/Entrez/DTDs/NCBI_BioTree.mod.dtd
Bio_Eutils/Entrez/DTDs/NCBI_Blast4.dtd
Bio_Eutils/Entrez/DTDs/NCBI_Blast4.mod.dtd
Bio_Eutils/Entrez/DTDs/NCBI_BlastDL.dtd
Bio_Eutils/Entrez/DTDs/NCBI_BlastDL.mod.dtd
Bio_Eutils/Entrez/DTDs/NCBI_BlastOutput.dtd
Bio_Eutils/Entrez/DTDs/NCBI_BlastOutput.mod.dtd
Bio_Eutils/Entrez/DTDs/NCBI_Cdd.dtd
Bio_Eutils/Entrez/DTDs/NCBI_Cdd.mod.dtd
Bio_Eutils/Entrez/DTDs/NCBI_Cn3d.dtd
Bio_Eutils/Entrez/DTDs/NCBI_Cn3d.mod.dtd
