Metadata-Version: 1.1
Name: Bio-Eutils
Version: 1.65
Summary: Standalone version of the Biopython Eutils modules
Home-page: https://github.com/jmaupetit/Bio_Eutils
Author: Julien Maupetit
Author-email: julien@maupetit.net
License: Biopython
Keywords: biopython,Entrez,Eutils,Medline,NCBI
Platform: Platform independant
Classifier: Programming Language :: Python
Classifier: Programming Language :: Python :: 3
Classifier: Environment :: Other Environment
Classifier: Intended Audience :: Developers
Classifier: Intended Audience :: Science/Research
Classifier: Operating System :: OS Independent
Classifier: Topic :: Software Development :: Libraries :: Python Modules
Classifier: Topic :: Scientific/Engineering
